{
  "configVersion": 1,
  "timestamp": 1580220192457,
  "index": "/index.html",
  "assetGroups": [
    {
      "name": "app",
      "installMode": "prefetch",
      "updateMode": "prefetch",
      "urls": [
        "/favicon.ico",
        "/index.html",
        "/main-es2015.bb4113cf27d3a07e98f3.js",
        "/main-es5.bb4113cf27d3a07e98f3.js",
        "/manifest.webmanifest",
        "/polyfills-es2015.e320bd3f95e5b05465ac.js",
        "/polyfills-es5.5c4a0d280565d8c5faf5.js",
        "/runtime-es2015.edb2fcf2778e7bf1d426.js",
        "/runtime-es5.edb2fcf2778e7bf1d426.js",
        "/scripts.f2f002a99aa0f71bc45e.js",
        "/styles.ab00b2cec26586b8f4f5.css"
      ],
      "patterns": []
    },
    {
      "name": "assets",
      "installMode": "lazy",
      "updateMode": "prefetch",
      "urls": [
        "/assets/icons/icon-128x128.png",
        "/assets/icons/icon-144x144.png",
        "/assets/icons/icon-152x152.png",
        "/assets/icons/icon-192x192.png",
        "/assets/icons/icon-384x384.png",
        "/assets/icons/icon-512x512.png",
        "/assets/icons/icon-72x72.png",
        "/assets/icons/icon-96x96.png",
        "/fontawesome-webfont.674f50d287a8c48dc19b.eot",
        "/fontawesome-webfont.912ec66d7572ff821749.svg",
        "/fontawesome-webfont.af7ae505a9eed503f8b8.woff2",
        "/fontawesome-webfont.b06871f281fee6b241d6.ttf",
        "/fontawesome-webfont.fee66e712a8a08eef580.woff"
      ],
      "patterns": []
    }
  ],
  "dataGroups": [],
  "hashTable": {
    "/assets/icons/icon-128x128.png": "5ebf638bc2bc3ba22becbad6bfa85d583e024a09",
    "/assets/icons/icon-144x144.png": "396b78b3ff3f478f794dea0cf9863343fad4c7a3",
    "/assets/icons/icon-152x152.png": "c20f1e033e99063547687f6365f61aa51a9ecb01",
    "/assets/icons/icon-192x192.png": "fb99f255e224d217a80cf27d01c86a3b59d336e8",
    "/assets/icons/icon-384x384.png": "eb35d2d623e6bb7eb0190b2f16a77c678464d1f2",
    "/assets/icons/icon-512x512.png": "65716ee7bbe35d29479f931b61964a0bcfcaddcb",
    "/assets/icons/icon-72x72.png": "de0358f25b111ddf8f3f6e22e8a0b237139abf3b",
    "/assets/icons/icon-96x96.png": "29ac24802874e6a58e6efa93838cceeb8aa63d39",
    "/favicon.ico": "707a76a3d0ada973d53a40470b0e6c430d52c7bc",
    "/fontawesome-webfont.674f50d287a8c48dc19b.eot": "d980c2ce873dc43af460d4d572d441304499f400",
    "/fontawesome-webfont.912ec66d7572ff821749.svg": "98a8aa5cf7d62c2eff5f07ede8d844b874ef06ed",
    "/fontawesome-webfont.af7ae505a9eed503f8b8.woff2": "d6f48cba7d076fb6f2fd6ba993a75b9dc1ecbf0c",
    "/fontawesome-webfont.b06871f281fee6b241d6.ttf": "13b1eab65a983c7a73bc7997c479d66943f7c6cb",
    "/fontawesome-webfont.fee66e712a8a08eef580.woff": "28b782240b3e76db824e12c02754a9731a167527",
    "/index.html": "e87033732529fe9881987b5ecc21330c5c849ba0",
    "/main-es2015.bb4113cf27d3a07e98f3.js": "57d3906f965303f313c0bb76fd33bddbb1e865ee",
    "/main-es5.bb4113cf27d3a07e98f3.js": "f7eba58a2a2291018c6bf7921bc7bb3f9912423b",
    "/manifest.webmanifest": "44f2b7fddc9749ac1c324261146ab58d9d9f282a",
    "/polyfills-es2015.e320bd3f95e5b05465ac.js": "a0862b13f67073a295a596fc530b242b58dafb8f",
    "/polyfills-es5.5c4a0d280565d8c5faf5.js": "5a878471ebff40b6ed7915174437e2c310956182",
    "/runtime-es2015.edb2fcf2778e7bf1d426.js": "a9aafcf49f49145093fc831efd9b8e2f6c71bb9c",
    "/runtime-es5.edb2fcf2778e7bf1d426.js": "a9aafcf49f49145093fc831efd9b8e2f6c71bb9c",
    "/scripts.f2f002a99aa0f71bc45e.js": "d38f39dea23f395f7a037f2cbf98f740392cdb70",
    "/styles.ab00b2cec26586b8f4f5.css": "691e94455830aa6e9bed7b7891b909756aa24b13"
  },
  "navigationUrls": [
    {
      "positive": true,
      "regex": "^\\/.*$"
    },
    {
      "positive": false,
      "regex": "^\\/(?:.+\\/)?[^/]*\\.[^/]*$"
    },
    {
      "positive": false,
      "regex": "^\\/(?:.+\\/)?[^/]*__[^/]*$"
    },
    {
      "positive": false,
      "regex": "^\\/(?:.+\\/)?[^/]*__[^/]*\\/.*$"
    }
  ]
}